_itree.pypy38-pp73-darwin.so
py_itree-0.0.19.dist-info/RECORD
py_itree-0.0.19.dist-info/LICENSE
py_itree-0.0.19.dist-info/WHEEL
py_itree-0.0.19.dist-info/top_level.txt
py_itree-0.0.19.dist-info/METADATA
itree/tree.py
itree/version.py
itree/__init__.py
itree/node.py
tests/test_utils.py
tests/test_tree.py
tests/test_latency.py
tests/test_forest.py
tests/__init__.py
tests/test_picklable.py
tests/test_picklable_v2.py
tests/test_node.py
